Java12BianchengXuexiShouceChuyiFix1/README.md
Java12BianchengXuexiShouceChuyiFix1/__init__.py
Java12BianchengXuexiShouceChuyiFix1/__main__.py
Java12BianchengXuexiShouceChuyiFix1/file.epub
Java12BianchengXuexiShouceChuyiFix1/index.html
Java12BianchengXuexiShouceChuyiFix1/css/__init__.py
Java12BianchengXuexiShouceChuyiFix1/css/annotations.css
Java12BianchengXuexiShouceChuyiFix1/css/main.css
Java12BianchengXuexiShouceChuyiFix1/css/normalize.css
Java12BianchengXuexiShouceChuyiFix1/css/popup.css
Java12BianchengXuexiShouceChuyiFix1/font/__init__.py
Java12BianchengXuexiShouceChuyiFix1/font/fontello.eot
Java12BianchengXuexiShouceChuyiFix1/font/fontello.svg
Java12BianchengXuexiShouceChuyiFix1/font/fontello.ttf
Java12BianchengXuexiShouceChuyiFix1/font/fontello.woff
Java12BianchengXuexiShouceChuyiFix1/img/__init__.py
Java12BianchengXuexiShouceChuyiFix1/img/annotator-glyph-sprite.png
Java12BianchengXuexiShouceChuyiFix1/img/annotator-icon-sprite.png
Java12BianchengXuexiShouceChuyiFix1/img/apple-touch-icon.png
Java12BianchengXuexiShouceChuyiFix1/img/cancelfullscreen.png
Java12BianchengXuexiShouceChuyiFix1/img/close.png
Java12BianchengXuexiShouceChuyiFix1/img/fullscreen.png
Java12BianchengXuexiShouceChuyiFix1/img/loader.gif
Java12BianchengXuexiShouceChuyiFix1/img/menu-icon.png
Java12BianchengXuexiShouceChuyiFix1/img/save.png
Java12BianchengXuexiShouceChuyiFix1/img/saved.png
Java12BianchengXuexiShouceChuyiFix1/img/settings-s.png
Java12BianchengXuexiShouceChuyiFix1/img/settings.png
Java12BianchengXuexiShouceChuyiFix1/img/star.png
Java12BianchengXuexiShouceChuyiFix1/js/__init__.py
Java12BianchengXuexiShouceChuyiFix1/js/epub.js
Java12BianchengXuexiShouceChuyiFix1/js/epub.min.js
Java12BianchengXuexiShouceChuyiFix1/js/epub.min.map
Java12BianchengXuexiShouceChuyiFix1/js/hooks.min.js
Java12BianchengXuexiShouceChuyiFix1/js/hooks.min.map
Java12BianchengXuexiShouceChuyiFix1/js/reader.js
Java12BianchengXuexiShouceChuyiFix1/js/reader.js.map
Java12BianchengXuexiShouceChuyiFix1/js/reader.min.js
java_12_biancheng_xuexi_shouce_chuyi_fix1-2025.3.25.1.dist-info/METADATA
java_12_biancheng_xuexi_shouce_chuyi_fix1-2025.3.25.1.dist-info/WHEEL
java_12_biancheng_xuexi_shouce_chuyi_fix1-2025.3.25.1.dist-info/entry_points.txt
java_12_biancheng_xuexi_shouce_chuyi_fix1-2025.3.25.1.dist-info/top_level.txt
java_12_biancheng_xuexi_shouce_chuyi_fix1-2025.3.25.1.dist-info/RECORD
